MANIFEST.in
README.md
setup.cfg
setup.py
TOPSIS_Manpreet_101803174/topsis.py
TOPSIS_Manpreet_101803174.egg-info/PKG-INFO
TOPSIS_Manpreet_101803174.egg-info/SOURCES.txt
TOPSIS_Manpreet_101803174.egg-info/dependency_links.txt
TOPSIS_Manpreet_101803174.egg-info/entry_points.txt
TOPSIS_Manpreet_101803174.egg-info/requires.txt
TOPSIS_Manpreet_101803174.egg-info/top_level.txt