Metadata-Version: 2.1
Name: TOPSIS-Manpreet-101803174
Version: 1.0
Summary: A Python package implementing TOPSIS technique.
Home-page: UNKNOWN
Author: Manpreet Singh
Author-email: msingh_be18@gmail.com
License: MIT
Platform: UNKNOWN
Classifier: License :: OSI Approved :: MIT License
Classifier: Programming Language :: Python :: 3
Classifier: Programming Language :: Python :: 3.7
